{
    "n": [
        32,
        64,
        128,
        256,
        512,
        1024,
        2048,
        4096
    ],
    "add baseline": [
        299,
        587,
        1163,
        2315,
        4619,
        9227,
        18443,
        36875
    ],
    "add ssr": [
        124,
        220,
        412,
        796,
        1564,
        3100,
        6172,
        12316
    ],
    "add ssr frep": [
        60,
        92,
        156,
        284,
        540,
        1052,
        2076,
        4124
    ],
    "add parallel": [
        [
            1096,
            656,
            176,
            89,
            151
        ],
        [
            129,
            476,
            129,
            1066,
            4021
        ],
        [
            209,
            611,
            736,
            3751,
            8056
        ],
        [
            369,
            6346,
            13991,
            19561,
            1926
        ],
        [
            3781,
            22951,
            3596,
            14881,
            689
        ],
        [
            15056,
            27121,
            1329,
            34136,
            68156
        ],
        [
            21091,
            24131,
            6466,
            2609,
            28886
        ],
        [
            10921,
            5169,
            6676,
            9106,
            8671
        ]
    ],
    "add ssr parallel": [
        [
            968,
            1793,
            3833,
            3278,
            2318
        ],
        [
            7810,
            93,
            2665,
            4130,
            820
        ],
        [
            2879,
            489,
            644,
            117,
            274
        ],
        [
            19707,
            18837,
            8122,
            10842,
            165
        ],
        [
            261,
            261,
            261,
            2903,
            9463
        ],
        [
            47695,
            14715,
            17745,
            30210,
            9725
        ],
        [
            24019,
            31624,
            18954,
            32629,
            15194
        ],
        [
            28127,
            9777,
            9492,
            24202,
            20402
        ]
    ],
    "add ssr frep parallel": [
        [
            1383,
            933,
            933,
            3918,
            358
        ],
        [
            6997,
            507,
            727,
            2687,
            327
        ],
        [
            960,
            2770,
            905,
            1890,
            4365
        ],
        [
            1806,
            911,
            3731,
            99,
            99
        ],
        [
            19478,
            8618,
            3423,
            3593,
            7103
        ],
        [
            4452,
            20967,
            15302,
            14707,
            19902
        ],
        [
            30730,
            21030,
            69040,
            19785,
            32485
        ],
        [
            8121,
            16646,
            7466,
            21121,
            18351
        ]
    ],
    "add ssr frep omp": [
        [
            3080,
            260,
            43686,
            101388,
            3052
        ],
        [
            1400,
            486,
            4580,
            2412,
            1560
        ],
        [
            1942,
            1852,
            2998,
            1318,
            4500
        ],
        [
            288,
            1504,
            1444,
            820,
            2402
        ],
        [
            5134,
            1438,
            2166,
            2470,
            23218
        ],
        [
            6966,
            3910,
            2778,
            4566,
            2956
        ],
        [
            5688,
            14432,
            3266,
            6568,
            7826
        ],
        [
            14806,
            7170,
            7146,
            12484,
            7960
        ]
    ]
}